{
 "actions": [],
 "creation": "2024-10-17 20:08:28.362211",
 "default_view": "List",
 "doctype": "DocType",
 "editable_grid": 1,
 "engine": "InnoDB",
 "field_order": [
  "verification_type",
  "answer",
  "status",
  "note"
 ],
 "fields": [
  {
   "fieldname": "verification_type",
   "fieldtype": "Link",
   "in_list_view": 1,
   "label": "Verification Type",
   "options": "Verification Type",
   "read_only": 1,
   "reqd": 1
  },
  {
   "fieldname": "answer",
   "fieldtype": "Select",
   "label": "Answer",
   "options": "\nYes\nNo",
   "permlevel": 2
  },
  {
   "fieldname": "status",
   "fieldtype": "Link",
   "hidden": 1,
   "label": "Status",
   "options": "Workflow State"
  },
  {
   "fieldname": "note",
   "fieldtype": "Data",
   "in_list_view": 1,
   "label": "Note",
   "permlevel": 2
  }
 ],
 "index_web_pages_for_search": 1,
 "istable": 1,
 "links": [],
 "modified": "2024-10-24 22:15:58.196887",
 "modified_by": "Administrator",
 "module": "Laboratory",
 "name": "Application Verification",
 "owner": "Administrator",
 "permissions": [],
 "sort_field": "modified",
 "sort_order": "DESC",
 "states": [],
 "track_changes": 1
}